LICENSE
MANIFEST.in
README.md
setup.py
apimaticdemonstration1234/__init__.py
apimaticdemonstration1234/api_helper.py
apimaticdemonstration1234/apimaticdemonstration_1234_client.py
apimaticdemonstration1234/configuration.py
apimaticdemonstration1234/decorators.py
apimaticdemonstration1234.egg-info/PKG-INFO
apimaticdemonstration1234.egg-info/SOURCES.txt
apimaticdemonstration1234.egg-info/dependency_links.txt
apimaticdemonstration1234.egg-info/requires.txt
apimaticdemonstration1234.egg-info/top_level.txt
apimaticdemonstration1234/controllers/__init__.py
apimaticdemonstration1234/controllers/base_controller.py
apimaticdemonstration1234/controllers/delivery_reports_controller.py
apimaticdemonstration1234/controllers/messages_controller.py
apimaticdemonstration1234/controllers/replies_controller.py
apimaticdemonstration1234/exceptions/__init__.py
apimaticdemonstration1234/exceptions/api_exception.py
apimaticdemonstration1234/exceptions/send_messages_400_response_exception.py
apimaticdemonstration1234/http/__init__.py
apimaticdemonstration1234/http/http_call_back.py
apimaticdemonstration1234/http/http_client.py
apimaticdemonstration1234/http/http_context.py
apimaticdemonstration1234/http/http_method_enum.py
apimaticdemonstration1234/http/http_request.py
apimaticdemonstration1234/http/http_response.py
apimaticdemonstration1234/http/requests_client.py
apimaticdemonstration1234/models/__init__.py
apimaticdemonstration1234/models/cancel_scheduled_message_request.py
apimaticdemonstration1234/models/check_delivery_reports_response.py
apimaticdemonstration1234/models/check_replies_response.py
apimaticdemonstration1234/models/confirm_delivery_reports_as_received_request.py
apimaticdemonstration1234/models/confirm_delivery_reports_as_received_request_12.py
apimaticdemonstration1234/models/confirm_replies_as_received_request.py
apimaticdemonstration1234/models/confirm_replies_as_received_request_9.py
apimaticdemonstration1234/models/send_messages_request.py
apimaticdemonstration1234/models/send_messages_response.py
tests/__init__.py
tests/http_response_catcher.py
tests/test_helper.py
tests/controllers/__init__.py
tests/controllers/controller_test_base.py
tests/controllers/test_delivery_reports_controller.py
