Metadata-Version: 1.0
Name: apimaticdemonstration1234
Version: 1.0
Summary: TODO: Add a description
Home-page: https://apimatic.io
Author: APIMatic SDK Generator
Author-email: support@apimatic.io
License: UNKNOWN
Platform: UNKNOWN
